pysquel/__init__.py
pysquel/analyzer.py
pysquel/cli.py
pysquel/linter.py
pysquel-0.0.1.dist-info/METADATA
pysquel-0.0.1.dist-info/WHEEL
pysquel-0.0.1.dist-info/entry_points.txt
pysquel-0.0.1.dist-info/RECORD
