Metadata-Version: 2.1
Name: pysquel
Version: 0.0.1
Summary: 
Author: petr.prikryl
Author-email: nich@seznam.cz
Requires-Python: >=3.11,<4.0
Classifier: Programming Language :: Python :: 3
Classifier: Programming Language :: Python :: 3.11
Classifier: Programming Language :: Python :: 3.12
Requires-Dist: sqlfluff (>=2.3.5,<3.0.0)
Requires-Dist: typer (>=0.9.0,<0.10.0)
